msr_reader/__init__.py
msr_reader/obffile.py
msr_reader/xml_metadata.py
msr_reader-0.2.1.dist-info/METADATA
msr_reader-0.2.1.dist-info/WHEEL
msr_reader-0.2.1.dist-info/licenses/LICENSE
msr_reader-0.2.1.dist-info/RECORD
