Metadata-Version: 2.4
Name: msr-reader
Version: 0.2.1
Summary: Pure Python reader for MSR/OBF (Imspector) image data
Project-URL: Homepage, https://github.com/hoerlteam/msr-reader
Project-URL: Bug Tracker, https://github.com/hoerlteam/msr-reader/issues
Author-email: David Hörl <hoerldavid@gmail.com>
License-File: LICENSE
Classifier: Development Status :: 3 - Alpha
Classifier: License :: OSI Approved :: MIT License
Classifier: Operating System :: OS Independent
Classifier: Programming Language :: Python :: 3
Requires-Python: >=3.7
Requires-Dist: numpy
